Metadata-Version: 2.4
Name: episteme-ai
Version: 0.3.4
Summary: Hybrid reasoning and proof verification engine
Author: Víctor Mateu
License:                     GNU AFFERO GENERAL PUBLIC LICENSE
Project-URL: Homepage, https://github.com/victor-mateu/episteme
Project-URL: Repository, https://github.com/victor-mateu/episteme
Project-URL: Issues, https://github.com/victor-mateu/episteme/issues
Classifier: Development Status :: 3 - Alpha
Classifier: Intended Audience :: Science/Research
Classifier: Topic :: Scientific/Engineering :: Artificial Intelligence
Classifier: Topic :: Education
Classifier: License :: OSI Approved :: GNU Affero General Public License v3
Classifier: Programming Language :: Python :: 3
Classifier: Programming Language :: Python :: 3.10
Classifier: Programming Language :: Python :: 3.11
Requires-Python: >=3.10
License-File: LICENSE
Requires-Dist: fastapi>=0.110
Requires-Dist: uvicorn>=0.29
Requires-Dist: pydantic>=2.0
Dynamic: license-file
